{"cameraMode":{"drawMode":0,"name":"Shaded","section":"Shading Mode"},"sceneLighting":true,"audioPlay":false,"sceneViewState":{"m_AlwaysRefresh":false,"showFog":true,"showSkybox":true,"showFlares":true,"showImageEffects":true,"showParticleSystems":true,"showVisualEffectGraphs":true,"m_FxEnabled":true},"in2DMode":false,"pivot":{"x":4.050000190734863,"y":1.0,"z":-10.0},"rotation":{"x":0.005999913904815912,"y":0.004499891772866249,"z":-0.000026988376703229733,"w":0.9999727606773377},"size":2.9979801177978517,"orthographic":false}